calabi/__init__.py
calabi/hf_integration.py
calabi/transformers_support.py
calabi-1.0.0.dist-info/licenses/LICENSE
calabi_yau_compression/__init__.py
calabi_yau_compression/layers.py
calabi_yau_compression/utils.py
deployment/__init__.py
deployment/deployment_example.py
deployment/model_monitoring.py
deployment/model_serving.py
deployment/optimized_inference.py
deployment/simple_test.py
calabi-1.0.0.dist-info/METADATA
calabi-1.0.0.dist-info/WHEEL
calabi-1.0.0.dist-info/top_level.txt
calabi-1.0.0.dist-info/RECORD
