Metadata-Version: 2.4
Name: calabi
Version: 1.0.0
Summary: A novel approach to LLM compression using Calabi-Yau manifolds
Home-page: https://github.com/RoshanRaghavander/Calabi
Author: Roshan Raghavander
Author-email: roshanraghavander@gmail.com
License: MIT
Project-URL: Bug Reports, https://github.com/RoshanRaghavander/Calabi/issues
Project-URL: Source, https://github.com/RoshanRaghavander/Calabi
Project-URL: Documentation, https://github.com/RoshanRaghavander/Calabi/blob/main/API_REFERENCE.md
Keywords: llm-compression,deep-learning,pytorch,geometric-deep-learning,calabi-yau,neural-networks,model-compression,huggingface,transformers,bert,gpt
Classifier: Development Status :: 4 - Beta
Classifier: Intended Audience :: Developers
Classifier: Intended Audience :: Science/Research
Classifier: License :: OSI Approved :: MIT License
Classifier: Operating System :: OS Independent
Classifier: Programming Language :: Python :: 3
Classifier: Programming Language :: Python :: 3.8
Classifier: Programming Language :: Python :: 3.9
Classifier: Programming Language :: Python :: 3.10
Classifier: Programming Language :: Python :: 3.11
Classifier: Programming Language :: Python :: 3.12
Classifier: Topic :: Scientific/Engineering :: Artificial Intelligence
Classifier: Topic :: Software Development :: Libraries :: Python Modules
Requires-Python: >=3.8
License-File: LICENSE
Requires-Dist: torch>=1.12.0
Requires-Dist: numpy>=1.21.0
Provides-Extra: dev
Requires-Dist: pytest>=6.0; extra == "dev"
Requires-Dist: pytest-cov>=2.0; extra == "dev"
Requires-Dist: black>=22.0; extra == "dev"
Requires-Dist: flake8>=4.0; extra == "dev"
Provides-Extra: transformers
Requires-Dist: transformers>=4.0.0; extra == "transformers"
Requires-Dist: accelerate>=0.20.0; extra == "transformers"
Provides-Extra: examples
Requires-Dist: transformers>=4.0.0; extra == "examples"
Requires-Dist: datasets>=2.0.0; extra == "examples"
Requires-Dist: accelerate>=0.20.0; extra == "examples"
Dynamic: author
Dynamic: author-email
Dynamic: classifier
Dynamic: description
Dynamic: description-content-type
Dynamic: home-page
Dynamic: keywords
Dynamic: license
Dynamic: license-file
Dynamic: project-url
Dynamic: provides-extra
Dynamic: requires-dist
Dynamic: requires-python
Dynamic: summary
